odoo/addons/shopinvader_api_sale_loyalty/README.rst
odoo/addons/shopinvader_api_sale_loyalty/__init__.py
odoo/addons/shopinvader_api_sale_loyalty/__manifest__.py
odoo/addons/shopinvader_api_sale_loyalty/i18n/shopinvader_api_sale_loyalty.pot
odoo/addons/shopinvader_api_sale_loyalty/readme/CONTRIBUTORS.rst
odoo/addons/shopinvader_api_sale_loyalty/readme/DESCRIPTION.rst
odoo/addons/shopinvader_api_sale_loyalty/readme/USAGE.rst
odoo/addons/shopinvader_api_sale_loyalty/routers/__init__.py
odoo/addons/shopinvader_api_sale_loyalty/routers/cart.py
odoo/addons/shopinvader_api_sale_loyalty/routers/loyalty.py
odoo/addons/shopinvader_api_sale_loyalty/schemas/__init__.py
odoo/addons/shopinvader_api_sale_loyalty/schemas/loyalty_card.py
odoo/addons/shopinvader_api_sale_loyalty/schemas/loyalty_program.py
odoo/addons/shopinvader_api_sale_loyalty/schemas/loyalty_reward.py
odoo/addons/shopinvader_api_sale_loyalty/schemas/sale.py
odoo/addons/shopinvader_api_sale_loyalty/schemas/sale_line.py
odoo/addons/shopinvader_api_sale_loyalty/security/acl_loyalty_card.xml
odoo/addons/shopinvader_api_sale_loyalty/security/acl_loyalty_program.xml
odoo/addons/shopinvader_api_sale_loyalty/security/acl_loyalty_reward.xml
odoo/addons/shopinvader_api_sale_loyalty/security/acl_loyalty_rule.xml
odoo/addons/shopinvader_api_sale_loyalty/security/acl_product_product.xml
odoo/addons/shopinvader_api_sale_loyalty/security/acl_product_tag.xml
odoo/addons/shopinvader_api_sale_loyalty/security/acl_sale_loyalty_reward_wizard.xml
odoo/addons/shopinvader_api_sale_loyalty/security/acl_sale_order_coupon_points.xml
odoo/addons/shopinvader_api_sale_loyalty/security/groups.xml
odoo/addons/shopinvader_api_sale_loyalty/static/description/index.html
odoo/addons/shopinvader_api_sale_loyalty/tests/__init__.py
odoo/addons/shopinvader_api_sale_loyalty/tests/common.py
odoo/addons/shopinvader_api_sale_loyalty/tests/test_apply_coupon_or_reward.py
odoo/addons/shopinvader_api_sale_loyalty/tests/test_get_rewards.py
odoo_addon_shopinvader_api_sale_loyalty-16.0.1.2.0.dist-info/METADATA
odoo_addon_shopinvader_api_sale_loyalty-16.0.1.2.0.dist-info/WHEEL
odoo_addon_shopinvader_api_sale_loyalty-16.0.1.2.0.dist-info/top_level.txt
odoo_addon_shopinvader_api_sale_loyalty-16.0.1.2.0.dist-info/RECORD
