Metadata-Version: 2.1
Name: odoo-addon-shopinvader_api_sale_loyalty
Version: 16.0.1.2.0
Summary: FastAPI services to add coupons and loyalties to carts.
Home-page: https://github.com/shopinvader/odoo-shopinvader
Author: ACSONE SA/NV
License: AGPL-3
Classifier: Programming Language :: Python
Classifier: Framework :: Odoo
Classifier: Framework :: Odoo :: 16.0
Classifier: License :: OSI Approved :: GNU Affero General Public License v3
Requires-Python: >=3.10
Requires-Dist: extendable-pydantic>=1.2.0
Requires-Dist: fastapi
Requires-Dist: odoo-addon-extendable<16.1dev,>=16.0dev
Requires-Dist: odoo-addon-extendable-fastapi<16.1dev,>=16.0dev
Requires-Dist: odoo-addon-fastapi<16.1dev,>=16.0dev
Requires-Dist: odoo-addon-pydantic<16.1dev,>=16.0dev
Requires-Dist: odoo-addon-sale-loyalty-order-info<16.1dev,>=16.0dev
Requires-Dist: odoo-addon-shopinvader-api-cart<16.1dev,>=16.0dev
Requires-Dist: odoo-addon-shopinvader-api-security-sale<16.1dev,>=16.0dev
Requires-Dist: odoo-addon-shopinvader-schema-sale<16.1dev,>=16.0dev
Requires-Dist: odoo<16.1dev,>=16.0a
Requires-Dist: pydantic>=2.0.0
